src/example_package_Robin66014/__init__.py
src/example_package_Robin66014/example.py
dataqualityassessor-0.0.1.dist-info/METADATA
dataqualityassessor-0.0.1.dist-info/WHEEL
dataqualityassessor-0.0.1.dist-info/licenses/LICENSE
dataqualityassessor-0.0.1.dist-info/RECORD
