Metadata-Version: 2.1
Name: DataQualityAssessor
Version: 0.0.1
Summary: A small example package, initial version for Data Quality Tool
Project-URL: Homepage, https://github.com/Robin66014/DataQualityTool
Project-URL: Bug Tracker, https://github.com/pypa/sampleproject/issues
Author-email: Robin Kaelen <robin_kaelen@msn.com>
License-File: LICENSE
Classifier: License :: OSI Approved :: MIT License
Classifier: Operating System :: OS Independent
Classifier: Programming Language :: Python :: 3
Requires-Python: >=3.7
